{
  "publicPath": "/_nuxt/",
  "all": [
    "../server/index.spa.html",
    "../server/index.ssr.html",
    "17c2957.js",
    "26d49e9.js",
    "3225fbf.js",
    "3c295db.js",
    "5276e9c.js",
    "5c6ccda.js",
    "99e914d.js",
    "LICENSES",
    "b89204b.js"
  ],
  "initial": [
    "5276e9c.js",
    "3c295db.js",
    "26d49e9.js",
    "3225fbf.js"
  ],
  "async": [
    "17c2957.js",
    "5c6ccda.js",
    "99e914d.js",
    "b89204b.js"
  ],
  "modules": {
    "19871646": [
      3
    ],
    "26598303": [
      4
    ],
    "28890271": [
      5
    ],
    "31005122": [
      5
    ],
    "40568344": [
      8
    ],
    "51541077": [
      5
    ],
    "52286644": [
      5
    ],
    "52700494": [
      5
    ],
    "54801748": [
      5
    ],
    "56675980": [
      5
    ],
    "59436626": [
      5
    ],
    "60468961": [
      5
    ],
    "65394345": [
      5
    ],
    "77220740": [
      4
    ],
    "78564130": [
      5
    ],
    "87664682": [
      5
    ],
    "98635500": [
      5
    ],
    "02218d04": [
      5
    ],
    "233c4d4a": [
      4
    ],
    "5f0a47a0": [
      5
    ],
    "6fddc430": [
      5
    ],
    "013ebb45": [
      5
    ],
    "5cfc9d51": [
      5
    ],
    "28e45b42": [
      5
    ],
    "2e88334e": [
      5
    ],
    "1ff892a3": [
      5
    ],
    "7e6b2967": [
      5
    ],
    "62389b52": [
      5
    ],
    "6fd0f2f5": [
      5
    ],
    "0718f722": [
      5
    ],
    "499d12a4": [
      5
    ],
    "9e4c0e54": [
      5
    ],
    "4682448a": [
      5
    ],
    "72f614a5": [
      5
    ],
    "130e7c1b": [
      5
    ],
    "1992af58": [
      5
    ],
    "dda931bc": [
      5
    ],
    "02c38678": [
      5
    ],
    "2bbe3911": [
      5
    ],
    "3da2413c": [
      5
    ],
    "78203c1f": [
      5
    ],
    "e100f0a6": [
      5
    ],
    "387d83be": [
      5
    ],
    "318f46c9": [
      5
    ],
    "7b35a8f0": [
      5
    ],
    "03d2d689": [
      5
    ],
    "53d30122": [
      5
    ],
    "480b266f": [
      5
    ],
    "8d0fb9a8": [
      5
    ],
    "062958e4": [
      3
    ],
    "a82b3944": [
      5
    ],
    "745744fa": [
      5
    ],
    "49fe12ce": [
      5
    ],
    "3a006359": [
      5
    ],
    "a86b1c4e": [
      5
    ],
    "acdbdd8c": [
      5
    ],
    "331d98f8": [
      5
    ],
    "39fbb8fe": [
      5
    ],
    "033f94ee": [
      4
    ],
    "07e478ea": [
      4
    ],
    "12b41d50": [
      4
    ],
    "5e0c7165": [
      4
    ],
    "d34caa82": [
      4
    ],
    "8ea79a0c": [
      4
    ],
    "3696d5cf": [
      4
    ],
    "48903b97": [
      4
    ],
    "166eaa26": [
      4
    ],
    "12971f8f": [
      4
    ],
    "f9e6ad4e": [
      4
    ],
    "69f93149": [
      4
    ],
    "cf52bacc": [
      4
    ],
    "074eec1e": [
      4
    ],
    "9e03c0da": [
      4
    ],
    "4b85ba5b": [
      4
    ],
    "2f7a6a22": [
      4
    ],
    "27a66d42": [
      4
    ],
    "c7e247b4": [
      4
    ],
    "31dedadd": [
      5
    ],
    "76fece4c": [
      5
    ],
    "cff8a3a0": [
      5
    ],
    "ebb63c9a": [
      5
    ],
    "3466a504": [
      5
    ],
    "070052a8": [
      5
    ],
    "6064e160": [
      5
    ],
    "525f31c8": [
      5
    ],
    "3f741a6a": [
      5
    ],
    "7c26762a": [
      5
    ],
    "1c44b77a": [
      5
    ],
    "95876ffe": [
      5
    ],
    "ed7cf696": [
      5
    ],
    "9336f904": [
      5
    ],
    "0fee22a8": [
      5
    ],
    "eba7bc6e": [
      5
    ],
    "30cfb562": [
      5
    ],
    "139b85c3": [
      5
    ],
    "5695c982": [
      5
    ],
    "c09f7918": [
      5
    ],
    "e0e7bbf4": [
      5
    ],
    "09e4d9f0": [
      5
    ],
    "c488fb44": [
      5
    ],
    "a46b522e": [
      5
    ],
    "09df7e72": [
      5
    ],
    "729ee686": [
      5
    ],
    "7a6f3a62": [
      5
    ],
    "4c467da4": [
      3
    ],
    "4349e97f": [
      5
    ],
    "9575a7fc": [
      5
    ],
    "774ac3cc": [
      5
    ],
    "fbee8544": [
      5
    ],
    "6564d80b": [
      5
    ],
    "381836be": [
      5
    ],
    "7f86cb15": [
      5
    ],
    "7051a338": [
      5
    ],
    "1b7dfd95": [
      5
    ],
    "318d27b1": [
      5
    ],
    "c0ac8a0a": [
      5
    ],
    "751c763a": [
      5
    ],
    "1284d01d": [
      5
    ],
    "0c10b56b": [
      5
    ],
    "4a4cc0aa": [
      5
    ],
    "1a9632a2": [
      5
    ],
    "1d8ef339": [
      5
    ],
    "2779cd59": [
      5
    ],
    "80fdbcbe": [
      5
    ],
    "46f47306": [
      5
    ],
    "c2ce5740": [
      5
    ],
    "3597f4fd": [
      5
    ],
    "74c002a3": [
      5
    ],
    "08b6eeac": [
      5
    ],
    "2c8f3a2b": [
      5
    ],
    "92b00ec4": [
      5
    ],
    "1755e0c6": [
      5
    ],
    "69bfd45c": [
      5
    ],
    "34b8aff1": [
      5
    ],
    "28f1537d": [
      5
    ],
    "86c536c6": [
      5
    ],
    "19a3080e": [
      5
    ],
    "35a7428c": [
      5
    ],
    "c3436bb8": [
      5
    ],
    "e608d7e8": [
      5
    ],
    "6524d6c2": [
      5
    ],
    "fa6ceb30": [
      5
    ],
    "7ffbeb54": [
      3
    ],
    "0204e121": [
      3
    ],
    "2fa2f71c": [
      5
    ],
    "2155cea5": [
      5
    ],
    "356498e6": [
      4
    ],
    "4e95767a": [
      3
    ],
    "afeb249e": [
      3
    ],
    "24bed9ff": [
      3
    ],
    "a856e296": [
      3
    ],
    "5cdcc07e": [
      3
    ],
    "6d418ad6": [
      3
    ],
    "6b118d1d": [
      3
    ],
    "4d4b89da": [
      3
    ],
    "de522798": [
      3
    ],
    "3ca5ec3a": [
      3
    ],
    "b617d7aa": [
      3
    ],
    "7aa015fb": [
      5
    ],
    "4b34ea07": [
      5
    ],
    "345f8a2c": [
      5
    ],
    "67c8bc3e": [
      5
    ],
    "535e0070": [
      5
    ],
    "0bb7d222": [
      5
    ],
    "3e0f0f73": [
      5
    ],
    "663a765a": [
      5
    ],
    "0d9f6f34": [
      5
    ],
    "053d470b": [
      5
    ],
    "39e7bd1f": [
      5
    ],
    "20f5b05a": [
      5
    ],
    "c376149e": [
      5
    ],
    "10d09966": [
      5
    ],
    "2244ce8e": [
      5
    ],
    "3f9ee205": [
      5
    ],
    "59a7c46e": [
      5
    ],
    "072c9580": [
      5
    ],
    "3251ec75": [
      5
    ],
    "bf668c1a": [
      5
    ],
    "646afdc0": [
      5
    ],
    "1183d181": [
      5
    ],
    "d55084ea": [
      5
    ],
    "25b4cffe": [
      4
    ],
    "dbbf1e14": [
      3
    ],
    "2b182b4c": [
      5
    ],
    "663a0c42": [
      5
    ],
    "5b73c536": [
      5
    ],
    "525e46fd": [
      5
    ],
    "4d25cf62": [
      5
    ],
    "946e6d88": [
      5
    ],
    "29e5aed9": [
      5
    ],
    "b303c0a8": [
      5
    ],
    "19a108b5": [
      5
    ],
    "303a105b": [
      5
    ],
    "87df02aa": [
      5
    ],
    "7b9a55bc": [
      5
    ],
    "711c85bd": [
      5
    ],
    "37e58f89": [
      5
    ],
    "ec8b7cbe": [
      5
    ],
    "439f01c5": [
      5
    ],
    "0fab9d38": [
      5
    ],
    "88690f0c": [
      5
    ],
    "43f83b6e": [
      5
    ],
    "156a7266": [
      5
    ],
    "d429afda": [
      5
    ],
    "ecebdc6e": [
      5
    ],
    "7a0b17e5": [
      5
    ],
    "dacf4922": [
      5
    ],
    "7caf0685": [
      5
    ],
    "0d6e3500": [
      5
    ],
    "135b385f": [
      5
    ],
    "2283ff40": [
      5
    ],
    "3d436644": [
      5
    ],
    "326068a2": [
      5
    ],
    "34e7576a": [
      5
    ],
    "54d5fa1a": [
      5
    ],
    "7b915d1e": [
      5
    ],
    "059c6b22": [
      5
    ],
    "036bba18": [
      5
    ],
    "7268a328": [
      5
    ],
    "57dc799d": [
      5
    ],
    "515282f0": [
      5
    ],
    "2a15db82": [
      5
    ],
    "217a6ad8": [
      5
    ],
    "187b4cfc": [
      5
    ],
    "00318270": [
      4
    ],
    "7880db2b": [
      4
    ],
    "f7d96c98": [
      5
    ],
    "3730511c": [
      5
    ],
    "36c244e4": [
      5
    ],
    "5aeb7615": [
      3
    ],
    "f2589e02": [
      3
    ],
    "74029a4a": [
      3
    ],
    "bc947a82": [
      4
    ],
    "210c154b": [
      3
    ],
    "e74a95b0": [
      4
    ],
    "c5d8994c": [
      5
    ],
    "365bf4c7": [
      5
    ],
    "6c3d4d1d": [
      5
    ],
    "4d72e94d": [
      5
    ],
    "7f55edf6": [
      5
    ],
    "e7a56a12": [
      5
    ],
    "3ecee785": [
      5
    ],
    "fb529f10": [
      5
    ],
    "81e7ae62": [
      5
    ],
    "184db6e2": [
      5
    ],
    "a690bd36": [
      5
    ],
    "3a121456": [
      5
    ],
    "d45cb8f8": [
      5
    ],
    "b2463c78": [
      5
    ],
    "778ebd55": [
      5
    ],
    "10ab84db": [
      5
    ],
    "7d9bcb22": [
      5
    ],
    "6d32218a": [
      5
    ],
    "6594e27e": [
      5
    ],
    "5bac562c": [
      5
    ],
    "33443fde": [
      5
    ],
    "980d2fa4": [
      5
    ],
    "f7e211f6": [
      5
    ],
    "1163b535": [
      5
    ],
    "d8e5446e": [
      5
    ],
    "7cc6840a": [
      5
    ],
    "4d45dc77": [
      5
    ],
    "a4a3a646": [
      5
    ],
    "68d8c436": [
      5
    ],
    "49e27e97": [
      5
    ],
    "8c33b868": [
      5
    ],
    "2d722a72": [
      5
    ],
    "3ac8111d": [
      5
    ],
    "a9f4be56": [
      5
    ],
    "341d24df": [
      5
    ],
    "1b316abb": [
      5
    ],
    "f71f034a": [
      5
    ],
    "08ce86e6": [
      5
    ],
    "6aa87545": [
      5
    ],
    "4bee5b00": [
      5
    ],
    "32e833ca": [
      5
    ],
    "1cee5818": [
      5
    ],
    "785a2364": [
      5
    ],
    "24df7343": [
      5
    ],
    "ea849320": [
      5
    ],
    "06f0df8c": [
      5
    ],
    "9672d2fe": [
      5
    ],
    "a07446ac": [
      5
    ],
    "1fbfe3fb": [
      5
    ],
    "73bcdde7": [
      5
    ],
    "9ca9fd20": [
      4
    ],
    "7728dce8": [
      4
    ],
    "9cd2cbaa": [
      4
    ],
    "0f0b77a3": [
      4
    ],
    "f36fcdaa": [
      3
    ],
    "81ff48ba": [
      3
    ],
    "a4650c84": [
      5
    ],
    "6cb8a9bb": [
      5
    ],
    "afe4e574": [
      5
    ],
    "46f7342c": [
      5
    ],
    "26e663b6": [
      5
    ],
    "2f007b04": [
      5
    ],
    "86e79334": [
      5
    ],
    "63ebab82": [
      5
    ],
    "4326df41": [
      3
    ],
    "01c5861a": [
      3
    ],
    "7bc2a2cf": [
      10
    ],
    "222b21cf": [
      10
    ],
    "a7d01572": [
      10
    ],
    "fd9d0708": [
      2
    ],
    "349f0102": [
      2
    ],
    "786e230c": [
      2
    ],
    "2ca97417": [
      2
    ],
    "0ab6692d": [
      2
    ],
    "ddabbd9a": [
      8
    ],
    "09676ef4": [
      8
    ],
    "386b2562": [
      8
    ],
    "846b08ec": [
      8
    ],
    "4abe5e7a": [
      7
    ],
    "24eea484": [
      7
    ],
    "e2d2b61e": [
      7
    ],
    "29d9d0c2": [
      7
    ],
    "d1202e16": [
      7
    ],
    "3f52f4b3": [
      10
    ],
    "24b3afa0": [
      10
    ],
    "29f74b34": [
      10
    ]
  },
  "assetsMapping": {
    "bba68bf6": [
      "17c2957.js"
    ],
    "7ea24c87": [
      "26d49e9.js"
    ],
    "1a3ae26b": [
      "3225fbf.js"
    ],
    "085a35c4": [
      "3c295db.js"
    ],
    "6fca0322": [
      "5276e9c.js"
    ],
    "e81092fe": [
      "5c6ccda.js"
    ],
    "2a130dde": [
      "99e914d.js"
    ],
    "51bae372": [
      "b89204b.js"
    ]
  }
}